gmaps_locator/__init__.py
gmaps_locator/get_detail.py
gmaps_locator-0.0.2.dist-info/LICENSE.md
gmaps_locator-0.0.2.dist-info/METADATA
gmaps_locator-0.0.2.dist-info/WHEEL
gmaps_locator-0.0.2.dist-info/top_level.txt
gmaps_locator-0.0.2.dist-info/RECORD
