Metadata-Version: 2.1
Name: gmaps-locator
Version: 0.0.2
Summary: Get geocode from google map
Author: Akbar Tolandy
Author-email: <akbartolandy@gmail.com>
Project-URL: Homepage, https://github.com/AkbarTolandy/gmaps_locator.git
Keywords: python,gmaps,geocode
Classifier: Development Status :: 4 - Beta
Classifier: Intended Audience :: Developers
Classifier: Programming Language :: Python :: 3
Classifier: License :: OSI Approved :: MIT License
Classifier: Operating System :: OS Independent
License-File: LICENSE.md
Requires-Dist: requests-html
